curlpyconvert-4.1.3.dist-info/METADATA
curlpyconvert-4.1.3.dist-info/WHEEL
curlpyconvert-4.1.3.dist-info/entry_points.txt
curlpyconvert/.DS_Store
curlpyconvert/__init__.py
curlpyconvert/lib/__init__.py
curlpyconvert/lib/context.py
curlpyconvert/lib/curl_parser.py
curlpyconvert/lib/dogman.py
curlpyconvert/lib/grab.py
curlpyconvert/main.py
curlpyconvert/test/__init__.py
curlpyconvert/test/test_context.py
curlpyconvert/test/test_curl_parser.py
curlpyconvert/test/test_dogman.py
curlpyconvert/test/test_grab.py
curlpyconvert/test/test_main.py
curlpyconvert-4.1.3.dist-info/RECORD
